pip_check_updates/__init__.py
pip_check_updates/__main__.py
pip_check_updates/args.py
pip_check_updates/config.py
pip_check_updates/exceptions.py
pip_check_updates/filter.py
pip_check_updates/parser.py
pip_check_updates/style.py
pip_check_updates/version.py
pip_check_updates-0.28.0.dist-info/licenses/LICENSE
pip_check_updates-0.28.0.dist-info/METADATA
pip_check_updates-0.28.0.dist-info/WHEEL
pip_check_updates-0.28.0.dist-info/entry_points.txt
pip_check_updates-0.28.0.dist-info/top_level.txt
pip_check_updates-0.28.0.dist-info/RECORD
