Metadata-Version: 2.4
Name: pip-check-updates
Version: 0.28.0
Summary: A tool to upgrade dependencies to the latest versions
Author-email: Zeheng Li <imzehengl@gmail.com>
Maintainer-email: Zeheng Li <imzehengl@gmail.com>
Project-URL: repository, https://github.com/zehengl/pip-check-updates
Project-URL: homepage, https://zehengl.github.io/pip-check-updates/
Keywords: pip,updates
Classifier: Programming Language :: Python :: 3
Classifier: License :: OSI Approved :: MIT License
Classifier: Operating System :: OS Independent
Requires-Python: >=3.8
License-File: LICENSE
Requires-Dist: beautifulsoup4
Requires-Dist: packaging
Requires-Dist: pyyaml
Requires-Dist: requests
Requires-Dist: rich
Requires-Dist: toml
Requires-Dist: tqdm-loggable
Dynamic: license-file
